fireboard_cloud_api_client/__init__.py
fireboard_cloud_api_client/api.py
fireboard_cloud_api_client-0.0.1.dist-info/LICENSE
fireboard_cloud_api_client-0.0.1.dist-info/METADATA
fireboard_cloud_api_client-0.0.1.dist-info/WHEEL
fireboard_cloud_api_client-0.0.1.dist-info/top_level.txt
fireboard_cloud_api_client-0.0.1.dist-info/RECORD
