Metadata-Version: 2.1
Name: fireboard-cloud-api-client
Version: 0.0.1
Summary: A rest api client for your fireboard thermometer
Home-page: https://github.com/gordlea/python_fireboard_cloud_api_client
Author: gordlea
Author-email: jgordonlea@gmail.com
License: MIT
Project-URL: Bug Tracker, https://github.com/gordlea/python_fireboard_cloud_api_client/issues
Keywords: Fireboard cloud api async
Platform: UNKNOWN
Classifier: Development Status :: 3 - Alpha
Classifier: Intended Audience :: Developers
Classifier: License :: OSI Approved :: MIT License
Classifier: Programming Language :: Python :: 3
Classifier: Topic :: Home Automation
Requires-Python: >=3.4
License-File: LICENSE
Requires-Dist: aiohttp (>=3.8.0)
